terregex/__init__.py
terregex/_sre_dump.py
terregex/mlr.py
terregex/transform.py
terregex-0.0.5.dist-info/LICENSE
terregex-0.0.5.dist-info/METADATA
terregex-0.0.5.dist-info/WHEEL
terregex-0.0.5.dist-info/top_level.txt
terregex-0.0.5.dist-info/RECORD
