Metadata-Version: 2.1
Name: terregex
Version: 0.0.5
Summary: Regex transformation library
Home-page: https://github.com/m1kit/terregex
Author: mikit
Author-email: me@mikit.dev
License: UNKNOWN
Project-URL: Bug Tracker, https://github.com/m1kit/terregex/issues
Platform: UNKNOWN
Classifier: Programming Language :: Python :: 3
Classifier: License :: OSI Approved :: Apache Software License
Classifier: Operating System :: OS Independent
Requires-Python: >=3.9
License-File: LICENSE
